crossy/__init__.py
crossy/analyze.py
crossy/classes.py
crossy-0.0.1.dist-info/METADATA
crossy-0.0.1.dist-info/WHEEL
crossy-0.0.1.dist-info/entry_points.txt
crossy-0.0.1.dist-info/top_level.txt
crossy-0.0.1.dist-info/RECORD
