Metadata-Version: 2.1
Name: crossy
Version: 0.0.1
Summary: mRNA stability analysis
Home-page: https://github.com/realpython/reader
Author: Matthew Theisen
Author-email: mtheisen@ucla.edu
License: MIT
Platform: UNKNOWN
Classifier: License :: OSI Approved :: MIT License
Classifier: Programming Language :: Python :: 3
Classifier: Programming Language :: Python :: 3.7
Requires-Dist: pandas
Provides-Extra: dev
Requires-Dist: pylint ; extra == 'dev'
Requires-Dist: autopep8 ; extra == 'dev'
Requires-Dist: isort ; extra == 'dev'
Requires-Dist: black ; extra == 'dev'
